toxic_comment_collection/__init__.py
toxic_comment_collection/api_config.json
toxic_comment_collection/config.json
toxic_comment_collection/main_execution.py
toxic_comment_collection/sql_dump_to_csv.py
toxic_comment_collection/statistics_generator.py
toxic_comment_collection/datasets/__init__.py
toxic_comment_collection/datasets/albadi2018.py
toxic_comment_collection/datasets/alfina2017.py
toxic_comment_collection/datasets/basile2019.py
toxic_comment_collection/datasets/bretschneider2016lol.py
toxic_comment_collection/datasets/bretschneider2016wow.py
toxic_comment_collection/datasets/bretschneider2017.py
toxic_comment_collection/datasets/chung2019.py
toxic_comment_collection/datasets/coltekin2019.py
toxic_comment_collection/datasets/dataset.py
toxic_comment_collection/datasets/davidson2017.py
toxic_comment_collection/datasets/elsherief2018.py
toxic_comment_collection/datasets/fortuna2019.py
toxic_comment_collection/datasets/founta2018.py
toxic_comment_collection/datasets/gao2018.py
toxic_comment_collection/datasets/gibert2018.py
toxic_comment_collection/datasets/helpers.py
toxic_comment_collection/datasets/ibrohim2018.py
toxic_comment_collection/datasets/ibrohim2019.py
toxic_comment_collection/datasets/jha2017.py
toxic_comment_collection/datasets/kulkarni2021.py
toxic_comment_collection/datasets/kumar2018.py
toxic_comment_collection/datasets/mandl2019en.py
toxic_comment_collection/datasets/mandl2019ger.py
toxic_comment_collection/datasets/mandl2019hind.py
toxic_comment_collection/datasets/mathur2018.py
toxic_comment_collection/datasets/mubarak2017aljazeera.py
toxic_comment_collection/datasets/mubarak2017twitter.py
toxic_comment_collection/datasets/mulki2019.py
toxic_comment_collection/datasets/novak2021.py
toxic_comment_collection/datasets/ousidhoum2019.py
toxic_comment_collection/datasets/pitenis2020.py
toxic_comment_collection/datasets/qian2019.py
toxic_comment_collection/datasets/ross2017.py
toxic_comment_collection/datasets/sanguinetti2018.py
toxic_comment_collection-1.0.2.dist-info/LICENSE
toxic_comment_collection-1.0.2.dist-info/METADATA
toxic_comment_collection-1.0.2.dist-info/WHEEL
toxic_comment_collection-1.0.2.dist-info/top_level.txt
toxic_comment_collection-1.0.2.dist-info/RECORD
