Metadata-Version: 2.1
Name: toxic-comment-collection
Version: 1.0.2
Summary: This package provides access to a collection of more than 40 labeled datasets for classification of toxic comments, e.g., hate speech
Home-page: https://github.com/julian-risch/toxic-comment-collection
Author: Julian Risch, Philipp Schmidt
Author-email: julian.risch@hpi.de
License: UNKNOWN
Project-URL: Bug Tracker, https://github.com/julian-risch/toxic-comment-collection/issues
Project-URL: More Research, https://julianrisch.de
Platform: UNKNOWN
Classifier: Programming Language :: Python :: 3
Classifier: License :: OSI Approved :: MIT License
Classifier: Operating System :: OS Independent
Requires-Python: >=3.6
License-File: LICENSE
